Metadata-Version: 2.1
Name: sentry-dingtalk-new11
Version: 1.0.0
Summary: A Sentry extension which integrates with Dingtalk robot.
Home-page: https://github.com/zhangshj/sentry-dingtalk.git
Author: ZhangShiJie
Author-email: zhangshijie62302@offcn.com
License: BSD
Keywords: sentry dingding dingtalk
Platform: any
Classifier: Framework :: Django
Classifier: Intended Audience :: Developers
Classifier: Intended Audience :: System Administrators
Classifier: Operating System :: OS Independent
Classifier: Topic :: Software Development
Provides-Extra: test
